liah/Liah.py
liah/__init__.py
liah/dataset_utils.py
liah/evaluator.py
liah/plot_utils.py
liah/testLiah.py
liah/utils.py
liah/dataset/README.md
liah/dataset/daughter_of_the_dawn.txt
liah/dataset/when_everybody_knew.txt
liah-0.1.6.dist-info/LICENSE
liah-0.1.6.dist-info/METADATA
liah-0.1.6.dist-info/WHEEL
liah-0.1.6.dist-info/top_level.txt
liah-0.1.6.dist-info/RECORD
