Metadata-Version: 2.1
Name: liah
Version: 0.1.6
Summary: Insert a Lie in a Haystack and evaluate the model's ability to detect it.
Home-page: https://github.com/melvinebenezer/Liah-Lie_in_a_haystack
Author: James Melvin Priyarajan
Author-email: melvinebenezer@gmail.com
License: MIT
Keywords: llm,needle in a haystack
Requires-Python: >=3.6
License-File: LICENSE
Requires-Dist: openai >=1.16.1
Requires-Dist: matplotlib
Requires-Dist: tiktoken
Requires-Dist: tqdm
